tovi/__init__.py
tovi/main.py
tovi-0.1.1.dist-info/DESCRIPTION.rst
tovi-0.1.1.dist-info/METADATA
tovi-0.1.1.dist-info/RECORD
tovi-0.1.1.dist-info/WHEEL
tovi-0.1.1.dist-info/metadata.json
tovi-0.1.1.dist-info/top_level.txt
