Metadata-Version: 2.0
Name: tovi
Version: 0.1.1
Summary: upload video from different source in easy way
Home-page: https://github.com/scarsellifi/ToVI
Author: Marco Scarselli
Author-email: scarselli@gmail.com
License: MIT
Platform: UNKNOWN
Requires-Dist: pytube
Requires-Dist: video-indexer (==0.1.6)
